pyfirth/PyFirth.py
pyfirth/__init__.py
pyfirth-0.0.5.dist-info/LICENSE
pyfirth-0.0.5.dist-info/METADATA
pyfirth-0.0.5.dist-info/WHEEL
pyfirth-0.0.5.dist-info/top_level.txt
pyfirth-0.0.5.dist-info/RECORD
